pipinstall-1.0.0.data/purelib/pipinstall.py
pipinstall-1.0.0.data/purelib/pipuninstall.py
pipinstall-1.0.0.data/scripts/pipinstall.py
pipinstall-1.0.0.data/scripts/pipuninstall.py
pipinstall-1.0.0.dist-info/LICENSE
pipinstall-1.0.0.dist-info/METADATA
pipinstall-1.0.0.dist-info/WHEEL
pipinstall-1.0.0.dist-info/top_level.txt
pipinstall-1.0.0.dist-info/RECORD
