Metadata-Version: 2.1
Name: pipinstall
Version: 1.0.0
Summary: Installs pip packages on all your installed Python versions (Windows only)
Home-page: https://github.com/gaming32/pipinstall
Author: Gaming32
Author-email: gaming32i64@gmail.com
License: License :: OSI Approved :: MIT License
Platform: UNKNOWN
